README.rst
setup.py
prov2bigchaindb/__init__.py
prov2bigchaindb/version.py
prov2bigchaindb.egg-info/PKG-INFO
prov2bigchaindb.egg-info/SOURCES.txt
prov2bigchaindb.egg-info/dependency_links.txt
prov2bigchaindb.egg-info/not-zip-safe
prov2bigchaindb.egg-info/requires.txt
prov2bigchaindb.egg-info/top_level.txt
prov2bigchaindb/core/__init__.py
prov2bigchaindb/core/accounts.py
prov2bigchaindb/core/clients.py
prov2bigchaindb/core/exceptions.py
prov2bigchaindb/core/local_stores.py
prov2bigchaindb/core/utils.py
prov2bigchaindb/tests/__init__.py
prov2bigchaindb/tests/test_document_concept.py
prov2bigchaindb/tests/test_graph_concept.py
prov2bigchaindb/tests/test_role_concept.py
prov2bigchaindb/tests/core/__init__.py
prov2bigchaindb/tests/core/test_accounts.py
prov2bigchaindb/tests/core/test_clients.py
prov2bigchaindb/tests/core/test_local_stores.py
prov2bigchaindb/tests/core/test_utils.py