Metadata-Version: 2.1
Name: prov2bigchaindb
Version: 0.4.1
Summary: PROV 2 BigchainDB
Home-page: https://github.com/DLR-SC/prov2bigchaindb
Author: Martin Stoffers
Author-email: martin.stoffers@dlr.de
License: Apache License 2.0
Keywords: provenance,BigchainDB,blockchain,PROV,PROV-DM,PROV-JSON,PROV-XML,PROV-N
Platform: UNKNOWN
Classifier: Development Status :: 4 - Beta
Classifier: Topic :: Database
Classifier: Topic :: Software Development :: Libraries
Classifier: Topic :: Software Development :: Libraries :: Python Modules
Classifier: License :: OSI Approved :: Apache Software License
Classifier: Intended Audience :: Developers
Classifier: Programming Language :: Python :: 3.5
Classifier: Programming Language :: Python :: 3.6
Classifier: Programming Language :: Python :: 3 :: Only
Provides-Extra: dev
Provides-Extra: test
Provides-Extra: docs
